README.txt
setup.py
collective/__init__.py
collective.remove.kss.egg-info/PKG-INFO
collective.remove.kss.egg-info/SOURCES.txt
collective.remove.kss.egg-info/dependency_links.txt
collective.remove.kss.egg-info/entry_points.txt
collective.remove.kss.egg-info/namespace_packages.txt
collective.remove.kss.egg-info/not-zip-safe
collective.remove.kss.egg-info/requires.txt
collective.remove.kss.egg-info/top_level.txt
collective/remove/__init__.py
collective/remove/kss/__init__.py
collective/remove/kss/configure.zcml
collective/remove/kss/tests.py
collective/remove/kss/profiles/default/cssregistry.xml
collective/remove/kss/profiles/default/jsregistry.xml
collective/remove/kss/profiles/default/kssregistry.xml
collective/remove/kss/profiles/default/metadata.xml
docs/HISTORY.txt