Metadata-Version: 1.0
Name: collective.remove.kss
Version: 1.0
Summary: Like all other collective.remove it remove a feature from Plone.
Home-page: http://svn.plone.org/svn/collective/collective.remove/kss/trunk
Author: JeanMichel FRANCOIS
Author-email: jeanmichel.francois@makina-corpus.com
License: GPL
Platform: UNKNOWN
Classifier: Programming Language :: Python
